{"Monster": [
  {"name": "Squid",
   "imageName": "card_squid",
   "genre": "GOD",
   "attackType": "melee",
   "maxLvl": 1,
   "basicATK": 2,
   "basicHP": 4,
   "advATK": 2,
   "advHP": 4,
   "currentLvl": 1,
   "currentATK": 2,
   "currentHP": 4,
   "skills":[
   ],
   "description": "Squid...",
   "amount": 3,
   "isInit": "True"
 },
 {"name": "Black Mage",
  "imageName": "card_black_mage ",
  "genre": "GOD",
  "attackType": "ranged",
  "maxLvl": 2,
  "basicATK": 2,
  "basicHP": 3,
  "advATK": 3,
  "advHP": 3,
  "currentLvl": 1,
  "currentATK": 2,
  "currentHP": 3,
  "skills":[
  ],
  "description": "Black Mage...",
  "amount": 3,
  "isInit": "True"
},
{"name": "Takeminakata",
 "imageName": "card_takeminakata",
 "genre": "GOD",
 "attackType": "enemySingle",
 "maxLvl": 2,
 "basicATK": 1,
 "basicHP": 4,
 "advATK": 2,
 "advHP": 4,
 "currentLvl": 1,
 "currentATK": 1,
 "currentHP": 4,
 "skills":[
   {"name": "Takeminakata's Nagikama",
    "imageName": "card_takeminakata_nagikama",
    "cost": 1,
    "effects":[
      {"targetMonster": "hostile",
       "effectType": "modifyHP",
       "hpModifier": [0, 0, -255, -255],
       "atkModifier": [0, 0, 0, 0],
       "lvlModifier": [0, 0, 0, 0],
       "blockAmount": 0
       }
     ],
     "transferCards": [],
     "description": "Use 1 crystal to attack all enemies.",
     "amount": 1,
     "isInit": "False"
   }
 ],
 "description": "Takeminakata...",
 "amount": 1,
 "isInit": "False"
},
{"name": "Gamble Mage",
 "imageName": "card_gamble_mage",
 "genre": "GOD",
 "attackType": "melee",
 "maxLvl": 2,
 "basicATK": 2,
 "basicHP": 4,
 "advATK": 3,
 "advHP": 5,
 "currentLvl": 1,
 "currentATK": 2,
 "currentHP": 4,
 "skills":[
   {"name": "Roll Dice",
    "imageName": "card_roll_dice",
    "cost": 0,
    "effects":[
      {"targetMonster": "itself",
       "effectType": "modifyATK",
       "hpModifier": [0, 0, 0, 0],
       "atkModifier": [-1, 0, 0, 0],
       "lvlModifier": [0, 0, 0, 0],
       "blockAmount": 0
     },
     {"targetMonster": "ranged",
      "effectType": "modifyHP",
      "hpModifier": [0, 0, -255, -255],
      "atkModifier": [0, 0, 0, 0],
      "lvlModifier": [0, 0, 0, 0],
      "blockAmount": 0
    },
     ],
     "transferCards": [],
     "description": "Both melee and ranged attack, ranged ATK amount is small.",
     "amount": 1,
     "isInit": "False"
   }
 ],
 "description": "Gamble Mage...",
 "amount": 2,
 "isInit": "False"
},
{"name": "Reaver",
 "imageName": "card_reaver",
 "genre": "GOD",
 "attackType": "melee",
 "maxLvl": 2,
 "basicATK": 1,
 "basicHP": 5,
 "advATK": 3,
 "advHP": 5,
 "currentLvl": 1,
 "currentATK": 1,
 "currentHP": 5,
 "skills":[],
 "description": "Reaver...",
 "amount": 2,
 "isInit": "False"
},
{"name": "Dark Ninja",
 "imageName": "card_dark_ninja",
 "genre": "GOD",
 "attackType": "melee",
 "maxLvl": 2,
 "basicATK": 1,
 "basicHP": 4,
 "advATK": 1,
 "advHP": 5,
 "currentLvl": 1,
 "currentATK": 1,
 "currentHP": 4,
 "skills":[
   {"name": "Dark Ninja Dance",
    "imageName": "card_dark_ninja_dance",
    "cost": 1,
    "effects":[
      {"targetMonster": "itself",
       "effectType": "modifyATK",
       "hpModifier": [0, 0, 0, 0],
       "atkModifier": [1, 0, 0, 0],
       "lvlModifier": [0, 0, 0, 0],
       "blockAmount": 0
     },
     {"targetMonster": "hostile",
      "effectType": "modifyHP",
      "hpModifier": [0, 0, -255, -255],
      "atkModifier": [0, 0, 0, 0],
      "lvlModifier": [0, 0, 0, 0],
      "blockAmount": 0
    },
     ],
     "transferCards": [],
     "description": "Use 1 crystal to increase ATK by 1 and attack all monsters.",
     "amount": 1,
     "isInit": "False"
   }
 ],
 "description": "Dark Ninja...",
 "amount": 2,
 "isInit": "False"
},
{"name": "Hattori Hanzo",
 "imageName": "card_hattori_hanzo",
 "genre": "GOD",
 "attackType": "rear",
 "maxLvl": 2,
 "basicATK": 2,
 "basicHP": 2,
 "advATK": 3,
 "advHP": 3,
 "currentLvl": 1,
 "currentATK": 2,
 "currentHP": 2,
 "skills":[],
 "description": "Hattori Hanzo...",
 "amount": 2,
 "isInit": "False"
},
{"name": "Kagutsuchi",
 "imageName": "card_kagutsuchi",
 "genre": "GOD",
 "attackType": "ranged",
 "maxLvl": 2,
 "basicATK": 1,
 "basicHP": 6,
 "advATK": 2,
 "advHP": 5,
 "currentLvl": 1,
 "currentATK": 1,
 "currentHP": 6,
 "skills":[
   {"name": "Kagutsuchi's Flame",
    "imageName": "card_kagutsuchi_flame",
    "cost": 0,
    "effects":[
      {"targetMonster": "enemySingle",
       "effectType": "counterATK",
       "hpModifier": [0, 0, 0, 0],
       "atkModifier": [1, 0, 0, 0],
       "lvlModifier": [0, 0, 0, 0],
       "blockAmount": 0
     },
     {"targetMonster": "itself",
      "effectType": "bombSelf",
      "hpModifier": [0, 0, 0, 0],
      "atkModifier": [0, 0, 0, 0],
      "lvlModifier": [0, 0, 0, 0],
      "blockAmount": 0
    },
     ],
     "transferCards": [],
     "description": "Can explode when attacked and damage +1 damage.",
     "amount": 1,
     "isInit": "False"
   }
 ],
 "description": "Kagutsuchi...",
 "amount": 2,
 "isInit": "False"
},
{"name": "Ukai Magoroku",
 "imageName": "card_ukai_magoroku",
 "genre": "GOD",
 "attackType": "hostile",
 "maxLvl": 1,
 "basicATK": 2,
 "basicHP": 2,
 "advATK": 3,
 "advHP": 3,
 "currentLvl": 1,
 "currentATK": 2,
 "currentHP": 2,
 "skills":[],
 "description": "Ukai Magoroku...",
 "amount": 2,
 "isInit": "False"
},
{"name": "Izanagi",
 "imageName": "card_izanagi",
 "genre": "GOD",
 "attackType": "ranged",
 "maxLvl": 2,
 "basicATK": 1,
 "basicHP": 5,
 "advATK": 2,
 "advHP": 6,
 "currentLvl": 1,
 "currentATK": 1,
 "currentHP": 5,
 "skills":[],
 "description": "Izanagi...",
 "amount": 2,
 "isInit": "False"
},
{"name": "Ultimate Ranger",
 "imageName": "card_ultimate_ranger",
 "genre": "GOD",
 "attackType": "enemySingle",
 "maxLvl": 1,
 "basicATK": 1,
 "basicHP": 6,
 "advATK": 1,
 "advHP": 6,
 "currentLvl": 1,
 "currentATK": 1,
 "currentHP": 6,
 "skills":[],
 "description": "Ultimate Ranger...",
 "amount": 2,
 "isInit": "False"
},
{"name": "Dragonewt",
 "imageName": "card_dragonewt",
 "genre": "GOD",
 "attackType": "melee",
 "maxLvl": 2,
 "basicATK": 1,
 "basicHP": 5,
 "advATK": 2,
 "advHP": 6,
 "currentLvl": 1,
 "currentATK": 1,
 "currentHP": 5,
 "skills":[
   {"name": "Dragon Song",
    "imageName": "card_dragon_song",
    "cost": 2,
    "effects":[
      {"targetMonster": "itself",
       "effectType": "modifyATK",
       "hpModifier": [0, 0, 0, 0],
       "atkModifier": [2, 0, 0, 0],
       "lvlModifier": [0, 0, 0, 0],
       "blockAmount": 0
     },
     ],
     "transferCards": [],
     "description": "Can use 2 crystals to increase ATK by 2",
     "amount": 1,
     "isInit": "False"
   },
   {"name": "Dragon Song Lv2",
    "imageName": "card_dragon_song_lv2",
    "cost": 4,
    "effects":[
      {"targetMonster": "itself",
       "effectType": "modifyATK",
       "hpModifier": [0, 0, 0, 0],
       "atkModifier": [3, 0, 0, 0],
       "lvlModifier": [0, 0, 0, 0],
       "blockAmount": 0
     },
     ],
     "transferCards": [],
     "description": "Can use 4 crystals to increase ATK by 3.",
     "amount": 1,
     "isInit": "False"
   },
 ],
 "description": "Dragonewt...",
 "amount": 2,
 "isInit": "False"
},
{"name": "Squid Ver.2",
 "imageName": "card_squid_v2",
 "genre": "GOD",
 "attackType": "melee",
 "maxLvl": 1,
 "basicATK": 5,
 "basicHP": 5,
 "advATK": 5,
 "advHP": 5,
 "currentLvl": 1,
 "currentATK": 5,
 "currentHP": 5,
 "skills":[
 ],
 "description": "Squid Version 2...",
 "amount": 1,
 "isInit": "False"
},
]
}
